.gitignore
CHANGES.rst
CONTRIBUTORS.rst
README.rst
TODO.rst
bootstrap.py
buildout.cfg
setup.cfg
setup.py
docs/LICENSE.GPL
docs/LICENSE.txt
src/collective/__init__.py
src/collective.aaf.egg-info/PKG-INFO
src/collective.aaf.egg-info/SOURCES.txt
src/collective.aaf.egg-info/dependency_links.txt
src/collective.aaf.egg-info/entry_points.txt
src/collective.aaf.egg-info/namespace_packages.txt
src/collective.aaf.egg-info/not-zip-safe
src/collective.aaf.egg-info/requires.txt
src/collective.aaf.egg-info/top_level.txt
src/collective/aaf/__init__.py
src/collective/aaf/configure.zcml
src/collective/aaf/setuphandlers.py
src/collective/aaf/testing.py
src/collective/aaf/upgrades.py
src/collective/aaf/portlets/__init__.py
src/collective/aaf/portlets/shibbolethloginportlet.py
src/collective/aaf/profiles/default/collective.aaf_various.txt
src/collective/aaf/profiles/default/metadata.xml
src/collective/aaf/profiles/upgrade_portlet/metadata.xml
src/collective/aaf/profiles/upgrade_portlet/portlets.xml
src/collective/aaf/tests/__init__.py
src/collective/aaf/tests/base_shibbolethloginportlet.py
src/collective/aaf/tests/robot_test.txt
src/collective/aaf/tests/test_example.py
src/collective/aaf/tests/test_robot.py