Metadata-Version: 1.1
Name: collective.aaf
Version: 2.1
Summary: Authentication integration layer for the Australian Access Federation (AAF) and Plone
Home-page: https://github.com/collective/collective.aaf
Author: David Beitey
Author-email: david@davidjb.com
License: gpl
Keywords: plone aaf shibboleth authentication
Platform: UNKNOWN
Classifier: Environment :: Web Environment
Classifier: Operating System :: OS Independent
Classifier: Framework :: Zope2
Classifier: Framework :: Plone
Classifier: Framework :: Plone :: 4.2
Classifier: Framework :: Plone :: 4.3
Classifier: Programming Language :: Python
Classifier: Programming Language :: Python :: 2.6
Classifier: Programming Language :: Python :: 2.7
Classifier: Topic :: Software Development :: Libraries :: Python Modules
